autilsy/__init__.py
autilsy/annots.py
autilsy/common.py
autilsy/ui.py
autilsy/resource/__init__.py
autilsy/resource/image_bytes.py
autilsy-0.1.3.4.dist-info/METADATA
autilsy-0.1.3.4.dist-info/WHEEL
autilsy-0.1.3.4.dist-info/top_level.txt
autilsy-0.1.3.4.dist-info/RECORD
