Metadata-Version: 2.1
Name: autilsy
Version: 0.1.3.4
Summary: A brief utils of scripts
Author: admon
Author-email: admon@gmail.com
Requires-Dist: imutils
Requires-Dist: jsonpatch
Requires-Dist: uuid
Requires-Dist: opencv-python
Requires-Dist: numpy
Requires-Dist: tqdm
Requires-Dist: tabulate
Requires-Dist: shapely
Requires-Dist: pillow
Requires-Dist: scikit-learn
Requires-Dist: jsonpointer
